cache_manager.py
config.py
file_scanner.py
mcp_elaborate.py
mcp_search.py
mcp_searcher.py
output_generator.py
report_elaborator.py
mcp_codebase_searcher-0.1.5.dist-info/licenses/LICENSE
mcp_codebase_searcher-0.1.5.dist-info/METADATA
mcp_codebase_searcher-0.1.5.dist-info/WHEEL
mcp_codebase_searcher-0.1.5.dist-info/entry_points.txt
mcp_codebase_searcher-0.1.5.dist-info/top_level.txt
mcp_codebase_searcher-0.1.5.dist-info/RECORD
