Metadata-Version: 2.4
Name: mcp_codebase_searcher
Version: 0.1.5
Summary: A Python tool to scan codebases, search for text/regex patterns, and elaborate on findings using Google Gemini.
Author-email: Sakilmostak <skmahim71@gmail.com>
License-Expression: MIT
Project-URL: Homepage, https://github.com/sakilmostak/mcp-codebase-searcher
Project-URL: Bug Tracker, https://github.com/sakilmostak/mcp-codebase-searcher/issues
Classifier: Programming Language :: Python :: 3
Classifier: Operating System :: OS Independent
Classifier: Development Status :: 3 - Alpha
Classifier: Environment :: Console
Classifier: Intended Audience :: Developers
Classifier: Topic :: Software Development :: Build Tools
Classifier: Topic :: Text Processing :: Indexing
Classifier: Topic :: Utilities
Requires-Python: >=3.8
License-File: LICENSE
Requires-Dist: python-dotenv
Requires-Dist: google-generativeai
Requires-Dist: diskcache
Dynamic: license-file
